setup.py
flask_cfpurge/__init__.py
flask_cfpurge/purger.py
flask_cfpurge.egg-info/PKG-INFO
flask_cfpurge.egg-info/SOURCES.txt
flask_cfpurge.egg-info/dependency_links.txt
flask_cfpurge.egg-info/top_level.txt