Metadata-Version: 2.1
Name: flask-cfpurge
Version: 0.2
Summary: Automate Purging Your File Cache On Cloudflare To Easily Update Your Webpages
Home-page: https://github.com/M4cs/flask-cfpurger
Author: Max Bridgland
Author-email: mabridgland@protonmail.com
License: UNKNOWN
Platform: UNKNOWN
